psrdada_cpp/__init__.py
psrdada_cpp/ipc_client.py
psrdada_cpp/monitor_client.py
psrdada_cpp/mq_client.py
psrdada_cpp/shared_struct_client.py
psrdada_cpp/type_conversion.py
psrdada_cpp_utils-0.2.1.dist-info/licenses/LICENSE
psrdada_cpp_utils-0.2.1.dist-info/METADATA
psrdada_cpp_utils-0.2.1.dist-info/WHEEL
psrdada_cpp_utils-0.2.1.dist-info/top_level.txt
psrdada_cpp_utils-0.2.1.dist-info/RECORD
