Metadata-Version: 2.4
Name: psrdada-cpp-utils
Version: 0.2.1
Summary: Python tools for working with psrdada_cpp/dadaflow pipelines
Author-email: Ewan Barr <ebarr@mpifr-bonn.mpg.de>
License: MIT License
Project-URL: Homepage, https://gitlab.mpcdf.mpg.de/mpifr-bdg/psrdada_cpp
Project-URL: Documentation, https://gitlab.mpcdf.mpg.de/mpifr-bdg/psrdada_cpp
Project-URL: Repository, https://gitlab.mpcdf.mpg.de/mpifr-bdg/psrdada_cpp.git
Project-URL: Bug Tracker, https://gitlab.mpcdf.mpg.de/mpifr-bdg/psrdada_cpp/issues
Keywords: radio astronomy,psrdada,signal processing,dadaflow,psrdada_cpp
Requires-Python: >=3.8
License-File: LICENSE
Requires-Dist: numpy
Requires-Dist: posix_ipc>=1.0.0
Dynamic: license-file
